odoo9_addon_l10n_ch_zip-9.0.2.0.0.99.dev19-py2.7-nspkg.pth
odoo9_addon_l10n_ch_zip-9.0.2.0.0.99.dev19.dist-info/DESCRIPTION.rst
odoo9_addon_l10n_ch_zip-9.0.2.0.0.99.dev19.dist-info/METADATA
odoo9_addon_l10n_ch_zip-9.0.2.0.0.99.dev19.dist-info/RECORD
odoo9_addon_l10n_ch_zip-9.0.2.0.0.99.dev19.dist-info/WHEEL
odoo9_addon_l10n_ch_zip-9.0.2.0.0.99.dev19.dist-info/metadata.json
odoo9_addon_l10n_ch_zip-9.0.2.0.0.99.dev19.dist-info/namespace_packages.txt
odoo9_addon_l10n_ch_zip-9.0.2.0.0.99.dev19.dist-info/top_level.txt
odoo_addons/l10n_ch_zip/README.rst
odoo_addons/l10n_ch_zip/__init__.py
odoo_addons/l10n_ch_zip/__openerp__.py
odoo_addons/l10n_ch_zip/data/res.better.zip.csv
odoo_addons/l10n_ch_zip/i18n/ar.po
odoo_addons/l10n_ch_zip/i18n/bg.po
odoo_addons/l10n_ch_zip/i18n/bs.po
odoo_addons/l10n_ch_zip/i18n/ca.po
odoo_addons/l10n_ch_zip/i18n/cs.po
odoo_addons/l10n_ch_zip/i18n/da.po
odoo_addons/l10n_ch_zip/i18n/de.po
odoo_addons/l10n_ch_zip/i18n/en_GB.po
odoo_addons/l10n_ch_zip/i18n/es.po
odoo_addons/l10n_ch_zip/i18n/es_CR.po
odoo_addons/l10n_ch_zip/i18n/es_EC.po
odoo_addons/l10n_ch_zip/i18n/es_ES.po
odoo_addons/l10n_ch_zip/i18n/es_MX.po
odoo_addons/l10n_ch_zip/i18n/es_VE.po
odoo_addons/l10n_ch_zip/i18n/et.po
odoo_addons/l10n_ch_zip/i18n/fi.po
odoo_addons/l10n_ch_zip/i18n/fr.po
odoo_addons/l10n_ch_zip/i18n/fr_CH.po
odoo_addons/l10n_ch_zip/i18n/gl.po
odoo_addons/l10n_ch_zip/i18n/hr.po
odoo_addons/l10n_ch_zip/i18n/hr_HR.po
odoo_addons/l10n_ch_zip/i18n/hu.po
odoo_addons/l10n_ch_zip/i18n/id.po
odoo_addons/l10n_ch_zip/i18n/it.po
odoo_addons/l10n_ch_zip/i18n/ja.po
odoo_addons/l10n_ch_zip/i18n/l10n_ch_zip.pot
odoo_addons/l10n_ch_zip/i18n/lt.po
odoo_addons/l10n_ch_zip/i18n/mk.po
odoo_addons/l10n_ch_zip/i18n/mn.po
odoo_addons/l10n_ch_zip/i18n/nb.po
odoo_addons/l10n_ch_zip/i18n/nb_NO.po
odoo_addons/l10n_ch_zip/i18n/nl.po
odoo_addons/l10n_ch_zip/i18n/nl_BE.po
odoo_addons/l10n_ch_zip/i18n/nl_NL.po
odoo_addons/l10n_ch_zip/i18n/pl.po
odoo_addons/l10n_ch_zip/i18n/pt.po
odoo_addons/l10n_ch_zip/i18n/pt_BR.po
odoo_addons/l10n_ch_zip/i18n/pt_PT.po
odoo_addons/l10n_ch_zip/i18n/ro.po
odoo_addons/l10n_ch_zip/i18n/ru.po
odoo_addons/l10n_ch_zip/i18n/sk.po
odoo_addons/l10n_ch_zip/i18n/sl.po
odoo_addons/l10n_ch_zip/i18n/sr@latin.po
odoo_addons/l10n_ch_zip/i18n/sv.po
odoo_addons/l10n_ch_zip/i18n/th.po
odoo_addons/l10n_ch_zip/i18n/tr.po
odoo_addons/l10n_ch_zip/i18n/tr_TR.po
