Metadata-Version: 2.0
Name: odoo9-addon-l10n-ch-zip
Version: 9.0.2.0.0.99.dev19
Summary: Provides all Swiss postal codes for auto-completion
Home-page: http://www.camptocamp.com
Author:         Camptocamp,
Author-email: support@odoo-community.org
License: AGPL-3
Platform: UNKNOWN
Classifier: Programming Language :: Python
Classifier: Framework :: Odoo
Classifier: License :: OSI Approved :: GNU Affero General Public License v3
Requires-Python: ~=2.7
Requires-Dist: odoo (<9.1a,>=9.0a)
Requires-Dist: odoo9-addon-base-location
Requires-Dist: odoo9-addon-l10n-ch-states
